cloudpulse/__init__.py
cloudpulse/config.py
cloudpulse/opts.py
cloudpulse/version.py
cloudpulse/TestManager/TestManager.py
cloudpulse/TestManager/__init__.py
cloudpulse/api/__init__.py
cloudpulse/api/app.py
cloudpulse/api/auth.py
cloudpulse/api/config.py
cloudpulse/api/hooks.py
cloudpulse/api/controllers/__init__.py
cloudpulse/api/controllers/base.py
cloudpulse/api/controllers/link.py
cloudpulse/api/controllers/root.py
cloudpulse/api/controllers/v1/__init__.py
cloudpulse/api/controllers/v1/collection.py
cloudpulse/api/controllers/v1/cpulse.py
cloudpulse/api/controllers/v1/types.py
cloudpulse/api/controllers/v1/utils.py
cloudpulse/api/middleware/__init__.py
cloudpulse/api/middleware/auth_token.py
cloudpulse/api/middleware/parsable_error.py
cloudpulse/cmd/__init__.py
cloudpulse/cmd/api.py
cloudpulse/common/__init__.py
cloudpulse/common/clients.py
cloudpulse/common/cloudpulse_keystoneclient.py
cloudpulse/common/config.py
cloudpulse/common/context.py
cloudpulse/common/exception.py
cloudpulse/common/paths.py
cloudpulse/common/rpc.py
cloudpulse/common/rpc_service.py
cloudpulse/common/safe_utils.py
cloudpulse/common/service.py
cloudpulse/common/timerthread.py
cloudpulse/common/utils.py
cloudpulse/common/yamlutils.py
cloudpulse/common/plugin/__init__.py
cloudpulse/common/plugin/discover.py
cloudpulse/conductor/__init__.py
cloudpulse/conductor/api.py
cloudpulse/conductor/config.py
cloudpulse/conductor/cpulse_lock.py
cloudpulse/db/__init__.py
cloudpulse/db/api.py
cloudpulse/db/sqlalchemy/__init__.py
cloudpulse/db/sqlalchemy/api.py
cloudpulse/db/sqlalchemy/models.py
cloudpulse/objects/__init__.py
cloudpulse/objects/base.py
cloudpulse/objects/cpulse.py
cloudpulse/objects/cpulselock.py
cloudpulse/objects/fields.py
cloudpulse/objects/utils.py
cloudpulse/openstack/__init__.py
cloudpulse/openstack/api/__init__.py
cloudpulse/openstack/api/cinder_api.py
cloudpulse/openstack/api/credentials.py
cloudpulse-2016.1.1.dist-info/DESCRIPTION.rst
cloudpulse-2016.1.1.dist-info/METADATA
cloudpulse-2016.1.1.dist-info/RECORD
cloudpulse-2016.1.1.dist-info/WHEEL
cloudpulse-2016.1.1.dist-info/entry_points.txt
cloudpulse-2016.1.1.dist-info/metadata.json
cloudpulse-2016.1.1.dist-info/pbr.json
cloudpulse-2016.1.1.dist-info/top_level.txt
