Metadata-Version: 2.0
Name: cloudpulse
Version: 2016.1.1
Summary: a Health-Checking Service for OpenStack deployments.
Home-page: http://www.openstack.org/
Author: OpenStack
Author-email: openstack-dev@lists.openstack.org
License: UNKNOWN
Platform: UNKNOWN
Classifier: Environment :: OpenStack
Classifier: Intended Audience :: Information Technology
Classifier: Intended Audience :: System Administrators
Classifier: License :: OSI Approved :: Apache Software License
Classifier: Operating System :: POSIX :: Linux
Classifier: Programming Language :: Python
Classifier: Programming Language :: Python :: 2
Classifier: Programming Language :: Python :: 2.7
Classifier: Programming Language :: Python :: 3
Classifier: Programming Language :: Python :: 3.3
Classifier: Programming Language :: Python :: 3.4
Requires-Dist: MySQL-python
Requires-Dist: PyMySQL (>=0.6.2)
Requires-Dist: WSME (>=0.7)
Requires-Dist: ansible (<2.0.0.0)
Requires-Dist: eventlet (>=0.17.4)
Requires-Dist: keystonemiddleware (>=2.0.0,!=2.4.0)
Requires-Dist: oslo.concurrency (>=2.3.0)
Requires-Dist: oslo.config (>=2.3.0)
Requires-Dist: oslo.db (>=2.4.1)
Requires-Dist: oslo.messaging (!=2.8.0,!=2.8.1,!=2.6.0,!=2.6.1,!=1.17.0,!=1.17.1,>=1.16.0,!=3.1.0,!=2.9.0,!=2.7.0)
Requires-Dist: oslo.versionedobjects (>=0.9.0)
Requires-Dist: paramiko (>=1.13.0)
Requires-Dist: pbr (>=1.6)
Requires-Dist: pecan (>=1.0.0)
Requires-Dist: python-cinderclient (>=1.3.1)
Requires-Dist: python-glanceclient (>=0.18.0)
Requires-Dist: python-neutronclient (>=2.6.0)
Requires-Dist: python-novaclient (!=2.33.0,>=2.28.1)
